{
	"store": [
	{
		"id": 1, 
		"name": "Super Ball",
		"image": "/ball.png",
		"value": "2000",			
		"description": "Friendler toy, Increases Friendler mood"
	},
	{
		"id": 2,
		"name": "Friendler Food",
		"image": "/poffin.jpg",
		"value": "3000",			
		"description": "Food for Friendlers, Increases Friendler mood"
	},
	{
		"id": 3,
		"name": "Coupon",
		"image": "/coupon.jpg",
		"value": "3000",			
		"description": "Coupon for your venue"
	}
	{
		"id": 4,
		"name": "Mystery Gift",
		"image": "/gift.png",
		"value": "25000",			
		"description": "A gift your friendler put in the store, What's inside?"
	}
	]
}